README.md
setup.py
i0/__init__.py
i0/main.py
i0/settings.py
i0/utils.py
i0.egg-info/PKG-INFO
i0.egg-info/SOURCES.txt
i0.egg-info/dependency_links.txt
i0.egg-info/entry_points.txt
i0.egg-info/not-zip-safe
i0.egg-info/requires.txt
i0.egg-info/top_level.txt