Metadata-Version: 2.1
Name: i0
Version: 0.0.6
Summary: Simple data service.
Home-page: https://github.com/0oio/i0
Author: Mindey
Author-email: ~@mindey.com
License: MIT
Platform: UNKNOWN
Provides-Extra: test
